MakefileJiaochengCYuyanBianchengWang/README.md
MakefileJiaochengCYuyanBianchengWang/__init__.py
MakefileJiaochengCYuyanBianchengWang/__main__.py
MakefileJiaochengCYuyanBianchengWang/file.epub
MakefileJiaochengCYuyanBianchengWang/index.html
MakefileJiaochengCYuyanBianchengWang/css/__init__.py
MakefileJiaochengCYuyanBianchengWang/css/annotations.css
MakefileJiaochengCYuyanBianchengWang/css/main.css
MakefileJiaochengCYuyanBianchengWang/css/normalize.css
MakefileJiaochengCYuyanBianchengWang/css/popup.css
MakefileJiaochengCYuyanBianchengWang/font/__init__.py
MakefileJiaochengCYuyanBianchengWang/font/fontello.eot
MakefileJiaochengCYuyanBianchengWang/font/fontello.svg
MakefileJiaochengCYuyanBianchengWang/font/fontello.ttf
MakefileJiaochengCYuyanBianchengWang/font/fontello.woff
MakefileJiaochengCYuyanBianchengWang/img/__init__.py
MakefileJiaochengCYuyanBianchengWang/img/annotator-glyph-sprite.png
MakefileJiaochengCYuyanBianchengWang/img/annotator-icon-sprite.png
MakefileJiaochengCYuyanBianchengWang/img/apple-touch-icon.png
MakefileJiaochengCYuyanBianchengWang/img/cancelfullscreen.png
MakefileJiaochengCYuyanBianchengWang/img/close.png
MakefileJiaochengCYuyanBianchengWang/img/fullscreen.png
MakefileJiaochengCYuyanBianchengWang/img/loader.gif
MakefileJiaochengCYuyanBianchengWang/img/menu-icon.png
MakefileJiaochengCYuyanBianchengWang/img/save.png
MakefileJiaochengCYuyanBianchengWang/img/saved.png
MakefileJiaochengCYuyanBianchengWang/img/settings-s.png
MakefileJiaochengCYuyanBianchengWang/img/settings.png
MakefileJiaochengCYuyanBianchengWang/img/star.png
MakefileJiaochengCYuyanBianchengWang/js/__init__.py
MakefileJiaochengCYuyanBianchengWang/js/epub.js
MakefileJiaochengCYuyanBianchengWang/js/epub.min.js
MakefileJiaochengCYuyanBianchengWang/js/epub.min.map
MakefileJiaochengCYuyanBianchengWang/js/hooks.min.js
MakefileJiaochengCYuyanBianchengWang/js/hooks.min.map
MakefileJiaochengCYuyanBianchengWang/js/reader.js
MakefileJiaochengCYuyanBianchengWang/js/reader.js.map
makefile_jiaocheng_c_yuyan_biancheng_wang-2024.3.5.0.dist-info/METADATA
makefile_jiaocheng_c_yuyan_biancheng_wang-2024.3.5.0.dist-info/WHEEL
makefile_jiaocheng_c_yuyan_biancheng_wang-2024.3.5.0.dist-info/entry_points.txt
makefile_jiaocheng_c_yuyan_biancheng_wang-2024.3.5.0.dist-info/top_level.txt
makefile_jiaocheng_c_yuyan_biancheng_wang-2024.3.5.0.dist-info/RECORD
